mypacks/__init__.py
mypacks/mathfun.py
mypacks_pkg_aspurgs-0.0.1.dist-info/LICENSE
mypacks_pkg_aspurgs-0.0.1.dist-info/METADATA
mypacks_pkg_aspurgs-0.0.1.dist-info/WHEEL
mypacks_pkg_aspurgs-0.0.1.dist-info/top_level.txt
mypacks_pkg_aspurgs-0.0.1.dist-info/RECORD
